cfabric_mcp/__init__.py
cfabric_mcp/cache.py
cfabric_mcp/corpus_manager.py
cfabric_mcp/resources.py
cfabric_mcp/server.py
cfabric_mcp/tools.py
cfabric_mcp-0.1.7.dist-info/METADATA
cfabric_mcp-0.1.7.dist-info/WHEEL
cfabric_mcp-0.1.7.dist-info/entry_points.txt
cfabric_mcp-0.1.7.dist-info/top_level.txt
cfabric_mcp-0.1.7.dist-info/RECORD
