Metadata-Version: 2.4
Name: cfabric-mcp
Version: 0.1.7
Summary: MCP server for Context Fabric corpus operations
Author: Cody Kingham
License: MIT
Project-URL: Homepage, https://context-fabric.ai
Project-URL: Repository, https://github.com/Context-Fabric/context-fabric
Project-URL: Issues, https://github.com/Context-Fabric/context-fabric/issues
Classifier: Development Status :: 3 - Alpha
Classifier: Intended Audience :: Developers
Classifier: License :: OSI Approved :: MIT License
Classifier: Programming Language :: Python :: 3.13
Requires-Python: >=3.13
Requires-Dist: context-fabric>=0.2.0
Requires-Dist: mcp<2,>=1.0
Requires-Dist: uvicorn>=0.32.0
Provides-Extra: dev
Requires-Dist: pytest>=7.0; extra == "dev"
Requires-Dist: pytest-asyncio; extra == "dev"
Provides-Extra: docs
Requires-Dist: griffe>=1.0; extra == "docs"
Requires-Dist: griffe-typingdoc>=0.2; extra == "docs"
